{"input_params":{"method":"POST","post":{"device_udid":"23289FFF-3CB3-4E18-ADF2-FC633D21014D","device_os":"13.2.3","device_type":"iOS","access_token":"","connection_user_id":"5","app_version":"1.0","device_name":"Gayatri\u2019s iPhone","connection_type":"Unlike","ws_token":"","device_token":"93D30DE6E85C6A0B8674FB4C53C4C03238C69F362D70882C4E3D1986FE0EEACD"}},"output_response":{"settings":{"success":"1","message":"Connection added successfully"},"data":"","queries":[{"query":"SELECT `vName`,`vValue` FROM `mod_setting`","time(ms)":1.591,"count":8,"total(ms)":117.777},{"query":"INSERT INTO `api_accesslogs` (`vIPAddress`, `vAPIName`, `vAPIURL`, `dAccessDate`, `vPlatform`, `vBrowser`, `vFileName`) VALUES ('103.47.153.168', 'connections', 'http:\/\/18.211.58.235\/canoodle\/WS\/connections', '2020-12-04 07:32:16', 'Unknown OS Platform', 'Unknown Browser', 'connections-1607067136.json')","time(ms)":37.016},{"query":"SELECT `iUserId`,`eStatus` FROM `users` WHERE `vAccessToken` = 'c0d8ff08c4de4de3df1095c71ef007b9c9fa3568841f19aa4ac7d7c68c68967f'","time(ms)":1.351},{"query":"SELECT `usc`.`iConnectionId` AS `conn_id`,`usc`.`eConnectionType` AS `conn_type`,`usc`.`eConnectionResult` AS `conn_result` FROM `user_connections` AS `usc` WHERE `iConnectionUserId` IN('5') AND `iUserId` IN('17')","time(ms)":36.823},{"query":"SELECT `usc`.`iConnectionId` AS `conn_id`,`usc`.`eConnectionType` AS `conn_type`,`usc`.`eConnectionResult` AS `conn_result` FROM `user_connections` AS `usc` WHERE `iUserId` IN('5') AND `iConnectionUserId` IN('17')","time(ms)":1.245},{"query":"SELECT `u`.`eIsSubscribed` AS `u_is_subscribed`,`u`.`iLikesPerDay` AS `u_likes_per_day`,`u`.`iUserId` AS `u_users_id_1` FROM `users` AS `u` WHERE `u`.`iUserId` = '17'  LIMIT 1","time(ms)":1.026},{"query":"INSERT INTO `user_connections` (`dtAddedAt`, `eStatus`, `iUserId`, `iConnectionUserId`, `eConnectionType`) VALUES (NOW(), 'Active', '17', '5', 'Unlike')","time(ms)":37.608},{"query":"SELECT `vFileName` FROM `api_accesslogs` WHERE `iAccessLogId` = 6294","time(ms)":1.117}]}}