{"input_params":{"method":"POST","post":{"device_name":"Deepali\u2019s iPhone","ws_token":"","access_token":"","device_udid":"23E22C93-18B4-4304-8DED-FFDAB3855998","device_os":"14.0.1","connection_type":"Unblock","connection_user_id":"12","app_version":"1.0","device_token":"B23BD80E7C67C3961B58B4E9AB6BF79159315610C3E1A626D0B51E894B188639","device_type":"iOS"}},"output_response":{"settings":{"success":"1","message":"connection event updated successfully"},"data":"","queries":[{"query":"SELECT `vName`,`vValue` FROM `mod_setting`","time(ms)":1.382,"count":9,"total(ms)":20.304},{"query":"INSERT INTO `api_accesslogs` (`vIPAddress`, `vAPIName`, `vAPIURL`, `dAccessDate`, `vPlatform`, `vBrowser`, `vFileName`) VALUES ('103.142.120.94', 'connections', 'http:\/\/18.211.58.235\/canoodle\/WS\/connections', '2020-11-04 14:47:54', 'Unknown OS Platform', 'Unknown Browser', 'connections-1604501274.json')","time(ms)":4.991},{"query":"SELECT `iUserId`,`eStatus` FROM `users` WHERE `vAccessToken` = '4a74264289507592e5072563ffa60835b57098d6b003620bbd59e0037f8a41ca'","time(ms)":1.087},{"query":"SELECT `usc`.`iConnectionId` AS `conn_id`,`usc`.`eConnectionType` AS `conn_type`,`usc`.`eConnectionResult` AS `conn_result` FROM `user_connections` AS `usc` WHERE `iConnectionUserId` IN('12') AND `iUserId` IN('21')","time(ms)":1.068},{"query":"SELECT `usc`.`iConnectionId` AS `conn_id`,`usc`.`eConnectionType` AS `conn_type`,`usc`.`eConnectionResult` AS `conn_result` FROM `user_connections` AS `usc` WHERE `iUserId` IN('12') AND `iConnectionUserId` IN('21')","time(ms)":1.13},{"query":"SELECT `usb`.`iBlockId` AS `block_id` FROM `user_block` AS `usb` WHERE `iUserId` IN('21') AND `iConnectionUserId` IN('12')","time(ms)":0.99},{"query":"DELETE FROM `user_block` WHERE `iBlockId` = '13'","time(ms)":5.026},{"query":"UPDATE `user_connections` SET `dtUpdatedAt` = NOW(), `eConnectionType` = 'Like', `eConnectionResult` = 'Unmatch' WHERE `iConnectionId` = '254' AND `eStatus` IN('Active')","time(ms)":3.434},{"query":"SELECT `vFileName` FROM `api_accesslogs` WHERE `iAccessLogId` = 1738","time(ms)":1.196}]}}