{"input_params":{"method":"POST","post":{"device_type":"iOS","device_token":"5C676A047363616566A3E84C0D32995C8E42A9773A291E9C1ECA11EA6F3CD5A7","device_udid":"23289FFF-3CB3-4E18-ADF2-FC633D21014D","device_os":"13.2.3","access_token":"","device_name":"Gayatri\u2019s iPhone","connection_type":"Like","connection_user_id":"24","app_version":"1.0","ws_token":""}},"output_response":{"settings":{"success":"1","message":"messages_finish_success_1","fields":[]},"data":[],"queries":[{"query":"SELECT `vName`,`vValue` FROM `mod_setting`","time(ms)":1.378,"count":15,"total(ms)":41.495},{"query":"INSERT INTO `api_accesslogs` (`vIPAddress`, `vAPIName`, `vAPIURL`, `dAccessDate`, `vPlatform`, `vBrowser`, `vFileName`) VALUES ('103.47.153.190', 'connections', 'http:\/\/18.211.58.235\/canoodle\/WS\/connections', '2020-12-17 16:07:48', 'Unknown OS Platform', 'Unknown Browser', 'connections-1608221268.json')","time(ms)":4.929},{"query":"SELECT `iUserId`,`eStatus` FROM `users` WHERE `vAccessToken` = '5944906980bf907da4e55cdefe561207bce12c70cd3098b46bbc7f53c70c5b9c'","time(ms)":1.055},{"query":"SELECT `usc`.`iConnectionId` AS `conn_id`,`usc`.`eConnectionType` AS `conn_type`,`usc`.`eConnectionResult` AS `conn_result` FROM `user_connections` AS `usc` WHERE `iConnectionUserId` IN('24') AND `iUserId` IN('20')","time(ms)":0.978},{"query":"SELECT `usc`.`iConnectionId` AS `conn_id`,`usc`.`eConnectionType` AS `conn_type`,`usc`.`eConnectionResult` AS `conn_result` FROM `user_connections` AS `usc` WHERE `iUserId` IN('24') AND `iConnectionUserId` IN('20')","time(ms)":0.955},{"query":"SELECT `u`.`eIsSubscribed` AS `u_is_subscribed`,`u`.`iLikesPerDay` AS `u_likes_per_day`,`u`.`iUserId` AS `u_users_id_1` FROM `users` AS `u` WHERE `u`.`iUserId` = '20'  LIMIT 1","time(ms)":0.969},{"query":"INSERT INTO `user_connections` (`dtAddedAt`, `eStatus`, `iUserId`, `iConnectionUserId`, `eConnectionResult`, `eConnectionType`) VALUES (NOW(), 'Active', '20', '24', 'Match', 'Like')","time(ms)":5.672},{"query":"UPDATE `users` SET `iLikesPerDay` = 0 +1 WHERE `iUserId` = '20'","time(ms)":5.732},{"query":"UPDATE `user_connections` SET `dtUpdatedAt` = NOW(), `eConnectionType` = 'Like', `eConnectionResult` = 'Match' WHERE `iConnectionId` = '119' AND `eStatus` IN('Active')","time(ms)":5.737},{"query":"SELECT `s`.`iUserId` AS `s_users_id`,`r`.`iUserId` AS `r_users_id`,`r`.`vDeviceToken` AS `r_device_token`,`r`.`eIsSubscribed` AS `r_premium_status`,CONCAT(s.vFirstName,\" \",s.vLastName) AS s_name FROM `user_connections` AS `uc` LEFT JOIN `users` AS `s` ON `uc`.`iUserId` = `s`.`iUserId` LEFT JOIN `users` AS `r` ON `uc`.`iConnectionUserId`  = `r`.`iUserId` WHERE (uc.iUserId = 20 AND uc.iConnectionUserId = 24)  LIMIT 1","time(ms)":1.102},{"query":"SELECT `nt`.`tMessage` FROM `mod_push_notify_template` as `nt` WHERE `nt`.`vTemplateCode` = 'matched_user'","time(ms)":0.934},{"query":"INSERT INTO `notification` (`vNotificationMessage`, `iNotifierId`, `eNotificationType`, `dtAddedAt`, `dtUpdatedAt`, `eNotificationStatus`, `iUserId`) VALUES ('Jenny Doe has accepted your canoodle request', '24', 'Match', NOW(), NOW(), 'Active', '20')","time(ms)":4.811},{"query":"SELECT `ui`.`vProfileImage` AS `ui_image`,`ui`.`iUserId` AS `ui_users_id` FROM `users` AS `ui` WHERE `ui`.`iUserId` = '20'  LIMIT 1","time(ms)":0.922},{"query":"INSERT INTO `mod_push_notifications` (`vUniqueId`, `vDeviceId`, `eMode`, `eNotifyCode`, `vSound`, `vBadge`, `vTitle`, `tMessage`, `tVarsJSON`, `eDeviceType`, `dtAddDateTime`, `tSendJSON`, `dtExeDateTime`, `eStatus`) VALUES ('94054', '707595215C85603F970C99D10D9F502347C22E9E4F9D4ED258004065F9FEAE0D', 'live', 'USER', '', 0, '', 'Jenny Doe has accepted your canoodle request', '[{\\\"key\\\":\\\"type\\\",\\\"value\\\":\\\"Like\\\",\\\"send\\\":\\\"Yes\\\"},{\\\"key\\\":\\\"receiver_id\\\",\\\"value\\\":\\\"24\\\",\\\"send\\\":\\\"Yes\\\"},{\\\"key\\\":\\\"user_id\\\",\\\"value\\\":\\\"20\\\",\\\"send\\\":\\\"Yes\\\"},{\\\"key\\\":\\\"user_name\\\",\\\"value\\\":\\\"Jenny Doe\\\",\\\"send\\\":\\\"Yes\\\"},{\\\"key\\\":\\\"user_profile\\\",\\\"value\\\":null,\\\"send\\\":\\\"Yes\\\"},{\\\"key\\\":\\\"user_image\\\",\\\"value\\\":\\\"http:\\\\\/\\\\\/18.211.58.235\\\\\/canoodle\\\\\/WS\\\\\/image_resize\\\\\/?pic=aHR0cDovLzE4LjIxMS41OC4yMzUvY2Fub29kbGUvcHVibGljL2ltYWdlcy9ub2ltYWdlLmdpZg==&height=100&width=100&color=FFFFFF\\\",\\\"send\\\":\\\"Yes\\\"}]', 'iOS', '2020-12-17 16:07:48', '{\\\"aps\\\":{\\\"badge\\\":0,\\\"sound\\\":\\\"received.caf\\\",\\\"alert\\\":{\\\"body\\\":\\\"Jenny Doe has accepted your canoodle request\\\"}},\\\"code\\\":\\\"USER\\\",\\\"id\\\":\\\"94054\\\",\\\"type\\\":\\\"Like\\\",\\\"receiver_id\\\":\\\"24\\\",\\\"user_id\\\":\\\"20\\\",\\\"user_name\\\":\\\"Jenny Doe\\\",\\\"user_profile\\\":\\\"\\\",\\\"user_image\\\":\\\"http:\\\\\/\\\\\/18.211.58.235\\\\\/canoodle\\\\\/WS\\\\\/image_resize\\\\\/?pic=aHR0cDovLzE4LjIxMS41OC4yMzUvY2Fub29kbGUvcHVibGljL2ltYWdlcy9ub2ltYWdlLmdpZg==&height=100&width=100&color=FFFFFF\\\"}', '2020-12-17 16:07:48', 'Executed')","time(ms)":5.355},{"query":"SELECT `vFileName` FROM `api_accesslogs` WHERE `iAccessLogId` = 7262","time(ms)":0.966}]}}