{"input_params":{"method":"POST","post":{"connection_user_id":"24","connection_type":"Unlike","device_name":"Deepali\u2019s iPhone","device_type":"iOS","device_os":"14.2","app_version":"1.0","device_token":"5A255EDBE3D472024954AAEA11F296DFE3E37999B9BB2BFE70723AE119DDB8CA","access_token":"","ws_token":"","device_udid":"23E22C93-18B4-4304-8DED-FFDAB3855998"}},"output_response":{"settings":{"success":"1","message":"messages_finish_success_1","fields":[]},"data":[],"queries":[{"query":"SELECT `vName`,`vValue` FROM `mod_setting`","time(ms)":1.504,"count":7,"total(ms)":17.107},{"query":"INSERT INTO `api_accesslogs` (`vIPAddress`, `vAPIName`, `vAPIURL`, `dAccessDate`, `vPlatform`, `vBrowser`, `vFileName`) VALUES ('103.142.120.90', 'connections', 'http:\/\/18.211.58.235\/canoodle\/WS\/connections', '2020-12-18 05:08:59', 'Unknown OS Platform', 'Unknown Browser', 'connections-1608268139.json')","time(ms)":6.014},{"query":"SELECT `iUserId`,`eStatus` FROM `users` WHERE `vAccessToken` = '8f2d670d9f268bff499972e78fe2a9f2d4b4bb2df797573a818fb95449e778ff'","time(ms)":1.129},{"query":"SELECT `usc`.`iConnectionId` AS `conn_id`,`usc`.`eConnectionType` AS `conn_type`,`usc`.`eConnectionResult` AS `conn_result` FROM `user_connections` AS `usc` WHERE `iConnectionUserId` IN('24') AND `iUserId` IN('1')","time(ms)":1.129},{"query":"SELECT `usc`.`iConnectionId` AS `conn_id`,`usc`.`eConnectionType` AS `conn_type`,`usc`.`eConnectionResult` AS `conn_result` FROM `user_connections` AS `usc` WHERE `iUserId` IN('24') AND `iConnectionUserId` IN('1')","time(ms)":1.056},{"query":"INSERT INTO `user_connections` (`dtAddedAt`, `eStatus`, `iUserId`, `iConnectionUserId`, `eConnectionResult`, `eConnectionType`) VALUES (NOW(), 'Active', '1', '24', 'Unmatch', 'Unlike')","time(ms)":5.238},{"query":"SELECT `vFileName` FROM `api_accesslogs` WHERE `iAccessLogId` = 7282","time(ms)":1.037}]}}