{"input_params":{"method":"POST","post":{"device_name":"Deepali\u2019s iPhone","device_type":"iOS","device_token":"8FDA53BE15EA46D07AB780B49D5F0077BA51BABFB91FAACA203002513E4A35A8","user_id":"1","ws_token":"","app_version":"1.0","device_udid":"AD1951A2-9C39-4338-A14B-CB9A46A00235","device_os":"14.2","access_token":""}},"output_response":{"settings":{"success":"1","message":"You have successfully logged out!","fields":[]},"data":[],"queries":[{"query":"SELECT `vName`,`vValue` FROM `mod_setting`","time(ms)":74,"count":5,"total(ms)":87.45},{"query":"INSERT INTO `api_accesslogs` (`vIPAddress`, `vAPIName`, `vAPIURL`, `dAccessDate`, `vPlatform`, `vBrowser`, `vFileName`) VALUES ('103.142.120.91', 'logout', 'http:\/\/18.211.58.235\/canoodle\/WS\/logout', '2020-12-23 08:48:42', 'Unknown OS Platform', 'Unknown Browser', 'logout-1608713322.json')","time(ms)":5.714},{"query":"SELECT `iUserId`,`eStatus` FROM `users` WHERE `vAccessToken` = '8be1271297cc49bbc3aac720e200553b8dcf9285dbc58026533fbe2ca0566cb1'","time(ms)":1.068},{"query":"UPDATE `users` SET `vAccessToken` = '', `vDeviceToken` = '' WHERE `iUserId` = '1' AND `eStatus` IN('Active')","time(ms)":5.486},{"query":"SELECT `vFileName` FROM `api_accesslogs` WHERE `iAccessLogId` = 7892","time(ms)":1.182}]}}