{"input_params":{"method":"POST","post":{"app_version":"1.0","device_udid":"23289FFF-3CB3-4E18-ADF2-FC633D21014D","device_type":"iOS","access_token":"","device_os":"13.2.3","ws_token":"","user_id":"16","device_name":"Demo\u2019s iPhone","device_token":"93D30DE6E85C6A0B8674FB4C53C4C03238C69F362D70882C4E3D1986FE0EEACD"}},"output_response":{"settings":{"success":"1","message":"You have successfully logged out!","fields":[]},"data":[],"queries":[{"query":"SELECT `vName`,`vValue` FROM `mod_setting`","time(ms)":1.268,"count":5,"total(ms)":13.809},{"query":"INSERT INTO `api_accesslogs` (`vIPAddress`, `vAPIName`, `vAPIURL`, `dAccessDate`, `vPlatform`, `vBrowser`, `vFileName`) VALUES ('183.87.232.182', 'logout', 'http:\/\/18.211.58.235\/canoodle\/WS\/logout', '2020-11-04 09:11:44', 'Unknown OS Platform', 'Unknown Browser', 'logout-1604481104.json')","time(ms)":5.254},{"query":"SELECT `iUserId`,`eStatus` FROM `users` WHERE `vAccessToken` = '91e12b7bb3718f0b46b97273498810e10886824c9e687fec4b4c3da826b62ec0'","time(ms)":1.003},{"query":"UPDATE `users` SET `vAccessToken` = '', `vDeviceToken` = '' WHERE `iUserId` = '16' AND `eStatus` IN('Active')","time(ms)":5.268},{"query":"SELECT `vFileName` FROM `api_accesslogs` WHERE `iAccessLogId` = 1280","time(ms)":1.016}]}}