{"input_params":{"method":"POST","post":{"pet_description":"Hi\nHshbdbd\n\n\n\n\n\n\n\n\n\n\n\n\n\n\nHshbdbd\nGhsbsbh\n","pet_id":"15","breed":"Labrador","app_version":"1.0","pet_akc_registered":"yes","access_token":"","ws_token":"","pet_age":"1","device_os":"13.6.1","pet_name":"Sushi","device_token":"707595215C85603F970C99D10D9F502347C22E9E4F9D4ED258004065F9FEAE0D","device_type":"iOS","device_name":"iPhone","device_udid":"85056521-47DA-47F4-859B-093BB58F2A6F"}},"output_response":{"settings":{"success":"1","message":"get_update_finish_success","fields":[]},"data":[],"queries":[{"query":"SELECT `vName`,`vValue` FROM `mod_setting`","time(ms)":1.295,"count":6,"total(ms)":13.985000000000001},{"query":"INSERT INTO `api_accesslogs` (`vIPAddress`, `vAPIName`, `vAPIURL`, `dAccessDate`, `vPlatform`, `vBrowser`, `vFileName`) VALUES ('172.58.173.62', 'pets', 'http:\/\/18.211.58.235\/canoodle\/WS\/pets', '2020-11-18 19:48:33', 'Unknown OS Platform', 'Unknown Browser', 'pets-1605728913.json')","time(ms)":5.216},{"query":"SELECT `iUserId`,`eStatus` FROM `users` WHERE `vAccessToken` = 'ce2772eeb75b5153bc0c615619d7063caf1ef8f4fc5a42807f90ff4688719a8f'","time(ms)":0.957},{"query":"SELECT `h`.`iPetId` AS `pet_id` FROM `pet` AS `h` WHERE `iPetId` IN('15')","time(ms)":1.021},{"query":"UPDATE `pet` SET `iUserId` = '15', `vPetName` = 'Sushi', `vBreed` = 'Labrador', `vPetAge` = '1', `vPetDescription` = 'Hi\\nHshbdbd\\n\\n\\n\\n\\n\\n\\n\\n\\n\\n\\n\\n\\n\\n\\nHshbdbd\\nGhsbsbh\\n', `vAKCRegistered` = 'yes' WHERE `iPetId` = '15'","time(ms)":4.465},{"query":"SELECT `vFileName` FROM `api_accesslogs` WHERE `iAccessLogId` = 5139","time(ms)":1.031}]}}