{"input_params":{"method":"POST","post":{"pet_description":"","pet_akc_registered":"yes","app_version":"1.0","device_os":"13.6.1","breed":"Labrador","device_token":"DCF08894E38E48ABC0A41CE8268ADDEB98DB66E35E6AE073EF7E24CCD083249A","ws_token":"","pet_age":"1","device_name":"iPhone","access_token":"","pet_name":"Sushi","device_type":"iOS","device_udid":"85056521-47DA-47F4-859B-093BB58F2A6F"}},"output_response":{"settings":{"success":"1","message":"Pet added successfully"},"queries":[{"query":"SELECT `vName`,`vValue` FROM `mod_setting`","time(ms)":1.373,"count":5,"total(ms)":14.608},{"query":"INSERT INTO `api_accesslogs` (`vIPAddress`, `vAPIName`, `vAPIURL`, `dAccessDate`, `vPlatform`, `vBrowser`, `vFileName`) VALUES ('108.235.29.71', 'pets', 'http:\/\/18.211.58.235\/canoodle\/WS\/pets', '2020-11-18 14:17:44', 'Unknown OS Platform', 'Unknown Browser', 'pets-1605709064.json')","time(ms)":5.526},{"query":"SELECT `iUserId`,`eStatus` FROM `users` WHERE `vAccessToken` = '494ba6ff07193db675380c2d17adf873f826fce26f9b2f73fd6eebdaa7396ef1'","time(ms)":1.051},{"query":"INSERT INTO `pet` (`iUserId`, `vPetName`, `vBreed`, `vPetAge`, `vPetDescription`, `vAKCRegistered`) VALUES ('15', 'Sushi', 'Labrador', '1', '', 'yes')","time(ms)":5.549},{"query":"SELECT `vFileName` FROM `api_accesslogs` WHERE `iAccessLogId` = 4576","time(ms)":1.109}]}}