{"input_params":{"method":"POST","post":{"device_token":"5C676A047363616566A3E84C0D32995C8E42A9773A291E9C1ECA11EA6F3CD5A7","social_login_id":"001115.43868751454d4703a431931c804e1943.1358","social_login_type":"apple","device_os":"13.2.3","ws_token":"","device_type":"iOS","device_udid":"23289FFF-3CB3-4E18-ADF2-FC633D21014D","access_token":"","app_version":"1.0","device_name":"Gayatri\u2019s iPhone","device_model":"iPhone 7 Plus"}},"output_response":{"settings":{"success":"0","message":"Your account is no longer available. Please contact administrator ('admin@theappineers.com').","fields":[]},"data":[],"queries":[{"query":"SELECT `vName`,`vValue` FROM `mod_setting`","time(ms)":1.505,"count":4,"total(ms)":14.818999999999999},{"query":"INSERT INTO `api_accesslogs` (`vIPAddress`, `vAPIName`, `vAPIURL`, `dAccessDate`, `vPlatform`, `vBrowser`, `vFileName`) VALUES ('103.47.153.188', 'social_login', 'http:\/\/18.211.58.235\/canoodle\/WS\/social_login', '2020-12-23 08:45:35', 'Unknown OS Platform', 'Unknown Browser', 'social_login-1608713135.json')","time(ms)":5.22},{"query":"SELECT `u`.`iUserId` AS `u_user_id`,`u`.`vFirstName` AS `u_first_name`,`u`.`vLastName` AS `u_last_name`,`u`.`vUserName` AS `u_user_name`,`u`.`vEmail` AS `u_email`,`u`.`vMobileNo` AS `u_mobile_no`,`u`.`vProfileImage` AS `u_profile_image`,`u`.`dDob` AS `u_dob`,`u`.`tAddress` AS `u_address`,`u`.`vCity` AS `u_city`,`u`.`dLatitude` AS `u_latitude`,`u`.`dLongitude` AS `u_longitude`,`u`.`iStateId` AS `u_state_id`,`u`.`vStateName` AS `u_state`,`u`.`vZipCode` AS `u_zip_code`,`u`.`eEmailVerified` AS `u_email_verified`,`u`.`eDeviceType` AS `u_device_type`,`u`.`vDeviceModel` AS `u_device_model`,`u`.`vDeviceOS` AS `u_device_os`,`u`.`vDeviceToken` AS `u_device_token`,`u`.`eStatus` AS `u_status`,`u`.`dtAddedAt` AS `u_added_at`,`u`.`dtUpdatedAt` AS `u_updated_at`,('bd8ff3a384908ebc6ebd1fdf8fa06b501f7cb83f98a698bd4e88561f600e673b') AS auth_token1,`u`.`eSocialLoginType` AS `u_social_login_type`,`u`.`vSocialLoginId` AS `u_social_login_id`,`u`.`ePushNotify` AS `u_push_notify`,`u`.`eOneTimeTransaction` AS `e_one_time_transaction`,`u`.`tOneTimeTransaction` AS `t_one_time_transaction`,`u`.`vTermsConditionsVersion` AS `u_terms_conditions_version`,`u`.`vPrivacyPolicyVersion` AS `u_privacy_policy_version`,(concat(u.vFirstName,' ',u.vLastName)) AS email_user_name,`u`.`vGender` AS `u_gender`,`u`.`iAge` AS `u_age`,`u`.`eLogStatus` AS `u_log_status_updated`,`u`.`eIsSubscribed` AS `u_is_subscribed`,`u`.`tReceiptData` AS `u_receipt_data`,`u`.`vSubscriptionId` AS `u_subscription_id` FROM `users` AS `u` WHERE u.vSocialLoginId='001115.43868751454d4703a431931c804e1943.1358' AND u.eSocialLoginType IN('apple')   LIMIT 1","time(ms)":6.99},{"query":"SELECT `vFileName` FROM `api_accesslogs` WHERE `iAccessLogId` = 7813","time(ms)":1.104}]}}