{"input_params":{"method":"POST","post":{"page_code":"privacypolicy","ws_token":"","device_type":"iOS","device_name":"Gayatri\u2019s iPhone","device_os":"13.2.3","access_token":"","device_udid":"23289FFF-3CB3-4E18-ADF2-FC633D21014D","device_token":"93D30DE6E85C6A0B8674FB4C53C4C03238C69F362D70882C4E3D1986FE0EEACD","app_version":"1.0"}},"output_response":{"settings":{"success":"1","message":"Page is available.","fields":["page_content","page_title"]},"data":[{"page_content":"<p><\/p>\n<p>hello<\/p>\n<p><\/p>\n<p>test policy<\/p>\n<p><\/p>\n<p>test policy<\/p>","page_title":"Privacy Policy"}],"queries":[{"query":"SELECT `vName`,`vValue` FROM `mod_setting`","time(ms)":1.442,"count":5,"total(ms)":11.729},{"query":"INSERT INTO `api_accesslogs` (`vIPAddress`, `vAPIName`, `vAPIURL`, `dAccessDate`, `vPlatform`, `vBrowser`, `vFileName`) VALUES ('103.47.153.161', 'static_pages', 'http:\/\/18.211.58.235\/canoodle\/WS\/static_pages', '2020-11-24 11:52:15', 'Unknown OS Platform', 'Unknown Browser', 'static_pages-1606218735.json')","time(ms)":7.097},{"query":"SELECT `iUserId` FROM `users` WHERE `vAccessToken` = 'eeec2f8989b2e74a2fd5253686edf13632708cdd2008462e22272219711a772d'","time(ms)":1.045},{"query":"SELECT `mps`.`vContent` AS `mps_content`,`mps`.`vPageTitle` AS `mps_page_title` FROM `mod_page_settings` AS `mps` WHERE `mps`.`vPageCode` = 'privacypolicy' AND `mps`.`eStatus` IN('Active')  LIMIT 1","time(ms)":1.124},{"query":"SELECT `vFileName` FROM `api_accesslogs` WHERE `iAccessLogId` = 6037","time(ms)":1.021}]}}