{"input_params":{"method":"GET","get":{"gender_type":"All","search_radius":"691"}},"output_response":{"settings":{"success":"1","message":"get_users_list_details","fields":["user_id","user_name","user_image","description","city","age","state","connection_type_by_logged_user","connection_type_by_receiver_user","breeds_name","media","pet_id","pet_name","breed","pet_age","pet_category","pet_description","akc_registered"]},"data":[{"user_id":"1","user_name":"Deepali Prabhu","user_image":"https:\/\/appineers.s3.amazonaws.com\/canoodle\/user_profile\/978307200_5fb376d057326.png","description":"Live n Let Live","city":"Roswell","state":"Georgia","age":"35","connection_type_by_logged_user":"","connection_type_by_receiver_user":"Like","pet_id":"1","pet_name":"Johnny","breed":"Labrador","pet_age":"2","pet_category":"","pet_description":"My darlingfgfdgfdgfdgtytrytry","akc_registered":"yes","breeds_name":[""],"media":[{"media_images":"https:\/\/appineers.s3.amazonaws.com\/canoodle\/media_images\/1\/media_1_5fb376f632212.png","media_id":"1","media_name":"","m_user_id":"1","media_type":"image\/png","media_url":"","video_thumbnail":""}]},{"user_id":"4","user_name":"Mia Turner","user_image":"","description":"I am cool","city":"Roswell","state":"Georgia","age":"30","connection_type_by_logged_user":"","connection_type_by_receiver_user":"","pet_id":"4","pet_name":"Mona","breed":"Shih Tzu","pet_age":"2","pet_category":"","pet_description":"My pet","akc_registered":"yes","breeds_name":[""],"media":[{"media_images":"https:\/\/appineers.s3.amazonaws.com\/canoodle\/media_images\/4\/media_1_5fb4cdfd318ce.png","media_id":"4","media_name":"","m_user_id":"4","media_type":"image\/png","media_url":"","video_thumbnail":""},{"media_images":"https:\/\/appineers.s3.amazonaws.com\/canoodle\/media_images\/4\/media_2_5fb4cdfd68e03.png","media_id":"5","media_name":"","m_user_id":"4","media_type":"image\/png","media_url":"","video_thumbnail":""}]},{"user_id":"5","user_name":"Ali Khan","user_image":"https:\/\/appineers.s3.amazonaws.com\/canoodle\/user_profile\/978307200_5fb4e92272152.png","description":"This is me","city":"Roswell","state":"Georgia","age":"22","connection_type_by_logged_user":"","connection_type_by_receiver_user":"","pet_id":"5","pet_name":"Wolf","breed":"Doberman","pet_age":"7","pet_category":"","pet_description":"My big boy","akc_registered":"no","breeds_name":[""],"media":[{"media_images":"https:\/\/appineers.s3.amazonaws.com\/canoodle\/media_images\/5\/media_1_5fb4d217c5619.png","media_id":"6","media_name":"","m_user_id":"5","media_type":"image\/png","media_url":"","video_thumbnail":""}]},{"user_id":"7","user_name":"Reynold James","user_image":"https:\/\/appineers.s3.amazonaws.com\/canoodle\/user_profile\/978307200_5fb4d65052318.png","description":"Hello","city":"Roswell","state":"Georgia","age":"26","connection_type_by_logged_user":"","connection_type_by_receiver_user":"","pet_id":"7","pet_name":"Tony","breed":"Labrador","pet_age":"4","pet_category":"","pet_description":"My best friend ","akc_registered":"no","breeds_name":[""],"media":[{"media_images":"https:\/\/appineers.s3.amazonaws.com\/canoodle\/media_images\/7\/media_1_5fb4d63669416.png","media_id":"9","media_name":"","m_user_id":"7","media_type":"image\/png","media_url":"","video_thumbnail":""},{"media_images":"https:\/\/appineers.s3.amazonaws.com\/canoodle\/media_images\/7\/media_2_5fb4d636a0f06.png","media_id":"10","media_name":"","m_user_id":"7","media_type":"image\/png","media_url":"","video_thumbnail":""}]},{"user_id":"8","user_name":"Dona Paula","user_image":"https:\/\/appineers.s3.amazonaws.com\/canoodle\/user_profile\/978307200_5fb4e1ba539f8.png","description":"About me","city":"Roswell","state":"Georgia","age":"25","connection_type_by_logged_user":"","connection_type_by_receiver_user":"Unlike","pet_id":"8","pet_name":"Tiger","breed":"Doberman","pet_age":"5","pet_category":"","pet_description":"About me","akc_registered":"yes","breeds_name":[""]}],"queries":[{"query":"SELECT `vName`,`vValue` FROM `mod_setting`","time(ms)":1.362,"count":16,"total(ms)":23.392},{"query":"INSERT INTO `api_accesslogs` (`vIPAddress`, `vAPIName`, `vAPIURL`, `dAccessDate`, `vPlatform`, `vBrowser`, `vFileName`) VALUES ('108.235.29.71', 'user_list', 'http:\/\/18.211.58.235\/canoodle\/WS\/user_list?gender_type=All&search_radius=691', '2020-11-23 13:20:26', 'Unknown OS Platform', 'Unknown Browser', 'user_list-1606137626.json')","time(ms)":5.252},{"query":"SELECT `iUserId`,`eStatus` FROM `users` WHERE `vAccessToken` = '1ccb979741eefad6546c2905d378cf3cb64c1477629987635006623a4d450c1e'","time(ms)":1.014},{"query":"SELECT `dLatitude`,`dLongitude` FROM `users` WHERE `iUserId` = '13'","time(ms)":0.99},{"query":"SELECT `m`.`vVideoThumbnail` AS `video_thumbnail`,`u`.`iUserId` AS `user_id`,(concat(u.vFirstName,' ',u.vLastName)) AS user_name,`u`.`vFirstName` AS `u_first_name`,`u`.`vLastName` AS `u_last_name`,`u`.`vEmail` AS `u_email`,`u`.`vMobileNo` AS `u_mobile_no`,`u`.`vProfileImage` AS `user_image`,`u`.`vDescription` AS `description`,`u`.`dDob` AS `u_dob`,`u`.`tAddress` AS `u_address`,`u`.`vCity` AS `city`,`u`.`dLatitude` AS `u_latitude`,`u`.`dLongitude` AS `u_longitude`,`u`.`iStateId` AS `u_state_id`,`u`.`vStateName` AS `state`,`u`.`vZipCode` AS `u_zip_code`,`u`.`iAge` AS `age`,`u`.`eStatus` AS `u_status`,GROUP_CONCAT(DISTINCT  i.vBreedsName SEPARATOR ',') AS breed_name,GROUP_CONCAT( DISTINCT `m`.`iMediaId` SEPARATOR ',')  AS media_id,('') AS connection_type_by_logged_user,('') AS connection_type_by_receiver_user,`p`.`iPetId` AS `pet_id`,`p`.`vPetName` AS `pet_name`,`p`.`vBreed` AS `breed`,`p`.`vPetAge` AS `pet_age`,`p`.`vPetCategory` AS `pet_category`,`p`.`vPetDescription` AS `pet_description`,`p`.`vAKCRegistered` AS `akc_registered` FROM `users` AS `u` LEFT JOIN `user_breed` AS `ui` ON `ui`.`iUserId` = `u`.`iUserId` LEFT JOIN `breeds` AS `i` ON `i`.`iBreedsId` = `ui`.`iBreedsId` LEFT JOIN `user_media` AS `m` ON `m`.`iUserId` = `u`.`iUserId` LEFT JOIN `pet` AS `p` ON `p`.`iUserId` = `u`.`iUserId` WHERE FLOOR(             3959 * acos (               cos ( radians(34.02324310) )               * cos( radians( u.dLatitude ) )               * cos( radians( u.dLongitude ) - radians(-84.36155550))               + sin ( radians(34.02324310) )               * sin( radians( u.dLatitude ))             )) <= '691' AND u.iUserId not in (SELECT DISTINCT(u.iUserId) AS user_id                 FROM users AS u                 LEFT JOIN user_connections AS uc ON uc.iConnectionUserId = u.iUserId                  LEFT JOIN user_connections AS ub ON ub.iUserId = u.iUserId                  WHERE u.eStatus = 'Active' AND (`uc`.`iUserId` = '13' OR (`ub`.`eConnectionResult` = 'Block' AND ub.iConnectionUserId = '13'))) AND `u`.`iUserId` <> '13' AND `u`.`eStatus` = 'Active' GROUP BY `user_id`","time(ms)":3.603},{"query":"SELECT '' AS connection_type,                          (SELECT eConnectionType                          FROM user_connections                          WHERE eStatus='active' AND iUserId=13 AND  iConnectionUserId = 1) AS connection_type_by_logged_user,                         (SELECT eConnectionResult                          FROM user_connections                          WHERE eStatus='active' AND iUserId=13 AND  iConnectionUserId = 1) AS connection_result_by_logged_user,                         (SELECT eConnectionType                          FROM user_connections                          WHERE eStatus='active' AND iUserId=1 AND  iConnectionUserId = 13) AS connection_type_by_receiver_user,                         (SELECT eConnectionResult                          FROM user_connections                          WHERE eStatus='active' AND iUserId=1 AND  iConnectionUserId = 13) AS connection_result_by_receiver_user                                                  FROM user_connections LIMIT 1","time(ms)":1.136},{"query":"SELECT `m`.`iMediaId` AS `media_id`,`m`.`iUserId` AS `m_user_id`,`m`.`vMediaType` AS `media_type`,`m`.`vVideoThumbnail` AS `video_thumbnail`,`m`.`vMediaUrl` AS `media_url`,`m`.`vMediaName` AS `media_name`,`m`.`vMediaFile` AS `media_file` FROM `user_media` AS `m` WHERE `m`.`iMediaId` = '1'","time(ms)":0.965},{"query":"SELECT '' AS connection_type,                          (SELECT eConnectionType                          FROM user_connections                          WHERE eStatus='active' AND iUserId=13 AND  iConnectionUserId = 4) AS connection_type_by_logged_user,                         (SELECT eConnectionResult                          FROM user_connections                          WHERE eStatus='active' AND iUserId=13 AND  iConnectionUserId = 4) AS connection_result_by_logged_user,                         (SELECT eConnectionType                          FROM user_connections                          WHERE eStatus='active' AND iUserId=4 AND  iConnectionUserId = 13) AS connection_type_by_receiver_user,                         (SELECT eConnectionResult                          FROM user_connections                          WHERE eStatus='active' AND iUserId=4 AND  iConnectionUserId = 13) AS connection_result_by_receiver_user                                                  FROM user_connections LIMIT 1","time(ms)":1.051},{"query":"SELECT `m`.`iMediaId` AS `media_id`,`m`.`iUserId` AS `m_user_id`,`m`.`vMediaType` AS `media_type`,`m`.`vVideoThumbnail` AS `video_thumbnail`,`m`.`vMediaUrl` AS `media_url`,`m`.`vMediaName` AS `media_name`,`m`.`vMediaFile` AS `media_file` FROM `user_media` AS `m` WHERE `m`.`iMediaId` IN ('4','5')","time(ms)":0.967},{"query":"SELECT '' AS connection_type,                          (SELECT eConnectionType                          FROM user_connections                          WHERE eStatus='active' AND iUserId=13 AND  iConnectionUserId = 5) AS connection_type_by_logged_user,                         (SELECT eConnectionResult                          FROM user_connections                          WHERE eStatus='active' AND iUserId=13 AND  iConnectionUserId = 5) AS connection_result_by_logged_user,                         (SELECT eConnectionType                          FROM user_connections                          WHERE eStatus='active' AND iUserId=5 AND  iConnectionUserId = 13) AS connection_type_by_receiver_user,                         (SELECT eConnectionResult                          FROM user_connections                          WHERE eStatus='active' AND iUserId=5 AND  iConnectionUserId = 13) AS connection_result_by_receiver_user                                                  FROM user_connections LIMIT 1","time(ms)":1.032},{"query":"SELECT `m`.`iMediaId` AS `media_id`,`m`.`iUserId` AS `m_user_id`,`m`.`vMediaType` AS `media_type`,`m`.`vVideoThumbnail` AS `video_thumbnail`,`m`.`vMediaUrl` AS `media_url`,`m`.`vMediaName` AS `media_name`,`m`.`vMediaFile` AS `media_file` FROM `user_media` AS `m` WHERE `m`.`iMediaId` = '6'","time(ms)":0.986},{"query":"SELECT '' AS connection_type,                          (SELECT eConnectionType                          FROM user_connections                          WHERE eStatus='active' AND iUserId=13 AND  iConnectionUserId = 7) AS connection_type_by_logged_user,                         (SELECT eConnectionResult                          FROM user_connections                          WHERE eStatus='active' AND iUserId=13 AND  iConnectionUserId = 7) AS connection_result_by_logged_user,                         (SELECT eConnectionType                          FROM user_connections                          WHERE eStatus='active' AND iUserId=7 AND  iConnectionUserId = 13) AS connection_type_by_receiver_user,                         (SELECT eConnectionResult                          FROM user_connections                          WHERE eStatus='active' AND iUserId=7 AND  iConnectionUserId = 13) AS connection_result_by_receiver_user                                                  FROM user_connections LIMIT 1","time(ms)":1.069},{"query":"SELECT `m`.`iMediaId` AS `media_id`,`m`.`iUserId` AS `m_user_id`,`m`.`vMediaType` AS `media_type`,`m`.`vVideoThumbnail` AS `video_thumbnail`,`m`.`vMediaUrl` AS `media_url`,`m`.`vMediaName` AS `media_name`,`m`.`vMediaFile` AS `media_file` FROM `user_media` AS `m` WHERE `m`.`iMediaId` IN ('9','10')","time(ms)":0.962},{"query":"SELECT '' AS connection_type,                          (SELECT eConnectionType                          FROM user_connections                          WHERE eStatus='active' AND iUserId=13 AND  iConnectionUserId = 8) AS connection_type_by_logged_user,                         (SELECT eConnectionResult                          FROM user_connections                          WHERE eStatus='active' AND iUserId=13 AND  iConnectionUserId = 8) AS connection_result_by_logged_user,                         (SELECT eConnectionType                          FROM user_connections                          WHERE eStatus='active' AND iUserId=8 AND  iConnectionUserId = 13) AS connection_type_by_receiver_user,                         (SELECT eConnectionResult                          FROM user_connections                          WHERE eStatus='active' AND iUserId=8 AND  iConnectionUserId = 13) AS connection_result_by_receiver_user                                                  FROM user_connections LIMIT 1","time(ms)":1.099},{"query":"SELECT `m`.`iMediaId` AS `media_id`,`m`.`iUserId` AS `m_user_id`,`m`.`vMediaType` AS `media_type`,`m`.`vVideoThumbnail` AS `video_thumbnail`,`m`.`vMediaUrl` AS `media_url`,`m`.`vMediaName` AS `media_name`,`m`.`vMediaFile` AS `media_file` FROM `user_media` AS `m` WHERE `m`.`iMediaId` = ''","time(ms)":0.962},{"query":"SELECT `vFileName` FROM `api_accesslogs` WHERE `iAccessLogId` = 6022","time(ms)":0.942}]}}